README.txt
setup.py
cursive/__init__.py
cursive.tools.egg-info/PKG-INFO
cursive.tools.egg-info/SOURCES.txt
cursive.tools.egg-info/dependency_links.txt
cursive.tools.egg-info/entry_points.txt
cursive.tools.egg-info/namespace_packages.txt
cursive.tools.egg-info/not-zip-safe
cursive.tools.egg-info/requires.txt
cursive.tools.egg-info/top_level.txt
cursive/tools/__init__.py
cursive/tools/cursive.py