Metadata-Version: 1.0
Name: cursive.tools
Version: 0.1
Summary: Tools for authoring restructured text files
Home-page: http://bitbucket.org/brandon/cursivetools/
Author: Brandon Craig Rhodes
Author-email: brandon@rhodesmill.org
License: UNKNOWN
Platform: UNKNOWN
